clipfree/__init__.py
clipfree/config_path.py
clipfree/blip/__init__.py
clipfree/blip/caption.py
clipfree/cache/__init__.py
clipfree/cache/cache.py
clipfree/clip/__init__.py
clipfree/clip/bulk.py
clipfree/clip/coca.py
clipfree/clip/image.py
clipfree/clip/interrogate.py
clipfree/clip/text.py
clipfree/clip/ranking_lists/artists.txt
clipfree/clip/ranking_lists/flavors.txt
clipfree/clip/ranking_lists/mediums.txt
clipfree/clip/ranking_lists/movements.txt
clipfree/clip/ranking_lists/sites.txt
clipfree/clip/ranking_lists/tags.txt
clipfree/clip/ranking_lists/techniques.txt
clipfree/model_manager/__init__.py
clipfree/model_manager/blip.py
clipfree/model_manager/clip.py
clipfree/utils/__init__.py
clipfree/utils/cast.py
clipfree/utils/blip/__init__.py
clipfree/utils/blip/blip.py
clipfree/utils/blip/med.py
clipfree/utils/blip/vit.py
horde_clipfree-0.0.2.dist-info/LICENSE
horde_clipfree-0.0.2.dist-info/METADATA
horde_clipfree-0.0.2.dist-info/WHEEL
horde_clipfree-0.0.2.dist-info/top_level.txt
horde_clipfree-0.0.2.dist-info/RECORD
