Metadata-Version: 2.1
Name: horde-clipfree
Version: 0.0.2
Summary: Workaround hlky abuse of DMCA
Author-email: db0 <mail@dbzer0.com>
License: GNU AFFERO GENERAL PUBLIC LICENSE
Project-URL: Homepage, https://github.com/db0/clipfree
Classifier: Programming Language :: Python :: 3
Classifier: License :: OSI Approved :: GNU Affero General Public License v3
Classifier: Operating System :: OS Independent
Classifier: Development Status :: 2 - Pre-Alpha
Requires-Python: <3.11,>=3.10
License-File: LICENSE
